setup.py
bin/catidb_ui
python/catidb_api/__init__.py
python/catidb_api/info.py
python/catidb_api/store_passwords.py
python/catidb_api.egg-info/PKG-INFO
python/catidb_api.egg-info/SOURCES.txt
python/catidb_api.egg-info/dependency_links.txt
python/catidb_api.egg-info/requires.txt
python/catidb_api.egg-info/top_level.txt
python/catidb_ui/__init__.py
python/catidb_ui/api_constants.py
python/catidb_ui/customqtablewidget.py
python/catidb_ui/portfolio.py
python/catidb_ui/roles.py
python/catidb_ui/security_users_panel.ui
python/catidb_ui/selector.py
python/catidb_ui/selector_container.py
python/catidb_ui/studies.py
share/icons/catidb_icon.png
share/icons/check_icon.png
share/icons/hide_menu_icon.png
share/icons/show_menu_icon.png