Metadata-Version: 1.0
Name: catidb-api
Version: 1.0.0
Summary: Client API for CATI data management servers
Home-page: https://cati.cea.fr
Author: CATI
Author-email: support@cati-neuroimaging.com
License: CeCILL-B
Platform: UNKNOWN
